saturdays/__init__.py
saturdays-0.0.1a1.dist-info/METADATA
saturdays-0.0.1a1.dist-info/WHEEL
saturdays-0.0.1a1.dist-info/RECORD
