Metadata-Version: 2.4
Name: saturdays
Version: 0.0.1a1
Summary: The landing page for the DRA Saturday Sessions
Project-URL: Documentation, https://github.com/ugognw/saturdays/README.md
Project-URL: PRs, https://github.com/ugognw/saturdays/pull
Project-URL: Issues, https://github.com/ugognw/saturdays/issues
Project-URL: Source, https://github.com/ugognw/saturdays
Author-email: Ugo Nwosu <ugognw@gmail.com>, Ugo Nwosu <ugn@sfu.ca>
Classifier: Development Status :: 3 - Alpha
Classifier: Intended Audience :: Science/Research
Classifier: Natural Language :: English
Classifier: Operating System :: POSIX
Classifier: Operating System :: Unix
Classifier: Programming Language :: Python
Classifier: Programming Language :: Python :: 3
Classifier: Programming Language :: Python :: 3 :: Only
Classifier: Programming Language :: Python :: 3.10
Classifier: Programming Language :: Python :: 3.11
Classifier: Programming Language :: Python :: 3.12
Classifier: Programming Language :: Python :: Implementation :: CPython
Classifier: Topic :: Scientific/Engineering :: Chemistry
Classifier: Topic :: Scientific/Engineering :: Physics
Requires-Python: >=3.10
Requires-Dist: ase>=3.23.0
Requires-Dist: cclib==1.8
Requires-Dist: numpy<2.0.0,>=1.24.2
Requires-Dist: pymatgen>=2024.6.10
Provides-Extra: dev
Requires-Dist: pre-commit>=3.7.0; extra == 'dev'
Provides-Extra: docs
Requires-Dist: mdx-truly-sane-lists>=1.3; extra == 'docs'
Requires-Dist: mkdocs-git-revision-date-plugin>=0.3.2; extra == 'docs'
Requires-Dist: mkdocs-material>=9.5.30; extra == 'docs'
Requires-Dist: mkdocs>=1.6.0; extra == 'docs'
Provides-Extra: test
Requires-Dist: pytest-cov>=5.0.0; extra == 'test'
Requires-Dist: pytest-datadir>=1.5.0; extra == 'test'
Requires-Dist: pytest-xdist>=3.6.1; extra == 'test'
Requires-Dist: pytest>=8.3.1; extra == 'test'
